[
  {
    "Number": 1,
    "Original Challenge": "rendering raycasting",
    "contributor": "grilly86",
    "link": "https://codepen.io/Grilly86/project/full/ApNRVn",
    "title": "ray casting game with maze generation",
    "authorURL": "https://codeblock.at/",
    "challengeURL": "https://thecodingtrain.com/CodingChallenges/146-rendering-ray-casting.html"
  },
  {
    "Number": 2,
    "Original Challenge": "maze generator",
    "contributor": "grilly86",
    "link": "https://codepen.io/Grilly86/full/rvmKex",
    "title": "",
    "authorURL": "",
    "challengeURL": ""
  },
  {
    "Number": 3,
    "Original Challenge": "blobby",
    "contributor": "grilly86",
    "link": "https://codepen.io/Grilly86/pen/bwAoKq",
    "title": "",
    "authorURL": "",
    "challengeURL": ""
  },
  {
    "Number": 4,
    "Original Challenge": "perlin noise loops",
    "contributor": "maximMonakov",
    "link": "https://maximmonakhov.github.io/SpaceGame/",
    "title": "",
    "authorURL": "",
    "challengeURL": ""
  },
  {
    "Number": 5,
    "Original Challenge": "10print",
    "contributor": "eugorgomes",
    "link": "https://editor.p5js.org/igor/present/kRaxw1_gu",
    "title": "",
    "authorURL": "",
    "challengeURL": ""
  },
  {
    "Number": 6,
    "Original Challenge": "random walk",
    "contributor": "mikakruschel",
    "link": "https://editor.p5js.org/mikakruschel/present/QchVIhVlH",
    "title": "",
    "authorURL": "",
    "challengeURL": ""
  },
  {
    "Number": 7,
    "Original Challenge": "fourier series",
    "contributor": "AHaliq",
    "link": "https://editor.p5js.org/AHaliq/present/1CZOJ2oDT",
    "title": "",
    "authorURL": "",
    "challengeURL": ""
  },
  {
    "Number": 8,
    "Original Challenge": "fireworks",
    "contributor": "brytlao",
    "link": "https://www.openprocessing.org/sketch/735262",
    "title": "",
    "authorURL": "",
    "challengeURL": ""
  },
  {
    "Number": 9,
    "Original Challenge": "flappy bird ai",
    "contributor": "sergei202",
    "link": "https://sergei202.com/flappy-bird/",
    "title": "",
    "authorURL": "",
    "challengeURL": ""
  },
  {
    "Number": 10,
    "Original Challenge": "astar",
    "contributor": "David Snyder",
    "link": "https://editor.p5js.org/davidgraygs4@gmail.com/present/WtbDxjSCs",
    "title": "",
    "authorURL": "",
    "challengeURL": ""
  },
  {
    "Number": 11,
    "Original Challenge": "fourier series",
    "contributor": "meznak",
    "link": "https://www.youtube.com/watch?v=d173h4fVxD8",
    "title": "",
    "authorURL": "",
    "challengeURL": ""
  },
  {
    "Number": 12,
    "Original Challenge": "convex hull",
    "contributor": "AfroDisco",
    "link": "https://editor.p5js.org/undefined/present/nSWqjnOJU",
    "title": "",
    "authorURL": "",
    "challengeURL": ""
  },
  {
    "Number": 13,
    "Original Challenge": "angry birds",
    "contributor": "Dizolivemint",
    "link": "https://angrybird.withkoji.com/",
    "title": "",
    "authorURL": "",
    "challengeURL": ""
  },
  {
    "Number": 14,
    "Original Challenge": "tic tac toe",
    "contributor": "David Snyder",
    "link": "https://editor.p5js.org/davidgraygs4@gmail.com/present/A0IzNW_l0",
    "title": "",
    "authorURL": "",
    "challengeURL": ""
  },
  {
    "Number": 15,
    "Original Challenge": "tic tac toe",
    "contributor": "TheTastefulToastie",
    "link": "https://editor.p5js.org/TheTastefulToastie/present/EZWUlidf1",
    "title": "",
    "authorURL": "",
    "challengeURL": ""
  },
  {
    "Number": 16,
    "Original Challenge": "tic tac toe",
    "contributor": "ilmnarayana",
    "link": "https://editor.p5js.org/ilmnarayana/present/o-pkHOuVq",
    "title": "",
    "authorURL": "",
    "challengeURL": ""
  },
  {
    "Number": 17,
    "Original Challenge": "tic tac toe",
    "contributor": "matt-mekha",
    "link": "https://editor.p5js.org/mmftl/present/a3mP-qjEM",
    "title": "",
    "authorURL": "",
    "challengeURL": ""
  },
  {
    "Number": 18,
    "Original Challenge": "tic tac toe",
    "contributor": "eightlay",
    "link": "https://editor.p5js.org/eightlaysome/present/iqXHSVn-6",
    "title": "",
    "authorURL": "",
    "challengeURL": ""
  },
  {
    "Number": 19,
    "Original Challenge": "tic tac toe",
    "contributor": "James-Lang",
    "link": "https://editor.p5js.org/James-Lang/present/swRhflZpi",
    "title": "",
    "authorURL": "",
    "challengeURL": ""
  },
  {
    "Number": 20,
    "Original Challenge": "tic tac toe",
    "contributor": "arthurrcavalcanti",
    "link": "https://editor.p5js.org/arthurrc/present/1ItYNEQGl",
    "title": "",
    "authorURL": "",
    "challengeURL": ""
  },
  {
    "Number": 21,
    "Original Challenge": "tic tac toe",
    "contributor": "Brogamer5000",
    "link": "https://editor.p5js.org/Brogamer5000/present/JB8-AddMS",
    "title": "",
    "authorURL": "",
    "challengeURL": ""
  },
  {
    "Number": 22,
    "Original Challenge": "tic tac toe",
    "contributor": "daviddostal",
    "link": "https://editor.p5js.org/daviddostal/present/F9mv0IRaJ",
    "title": "",
    "authorURL": "",
    "challengeURL": ""
  },
  {
    "Number": 23,
    "Original Challenge": "rubiks cube",
    "contributor": "zl25drexel",
    "link": "https://editor.p5js.org/zl25drexel/present/9K3PnFQQ_",
    "title": "",
    "authorURL": "",
    "challengeURL": ""
  },
  {
    "Number": 24,
    "Original Challenge": "tic tac toe",
    "contributor": "kabapy",
    "link": "https://editor.p5js.org/kabapy/present/sof5IFfwC",
    "title": "",
    "authorURL": "",
    "challengeURL": ""
  },
  {
    "Number": 25,
    "Original Challenge": "double pendulum",
    "contributor": "MisterBiggs",
    "link": "https://gitlab.com/MisterBiggs/double_pendulum/blob/master/animation.webm",
    "title": "",
    "authorURL": "",
    "challengeURL": ""
  },
  {
    "Number": 26,
    "Original Challenge": "tic tac toe",
    "contributor": "THSlimes",
    "link": "https://www.openprocessing.org/sketch/740544",
    "title": "",
    "authorURL": "",
    "challengeURL": ""
  },
  {
    "Number": 27,
    "Original Challenge": "10print",
    "contributor": "XMODS",
    "link": "https://codepen.io/XMODS/pen/wOjwVG",
    "title": "",
    "authorURL": "",
    "challengeURL": ""
  },
  {
    "Number": 28,
    "Original Challenge": "minesweeper",
    "contributor": "Zykatious",
    "link": "https://editor.p5js.org/Zykatious/present/vaRBSL6d8",
    "title": "",
    "authorURL": "",
    "challengeURL": ""
  },
  {
    "Number": 29,
    "Original Challenge": "Lissajous Curves",
    "contributor": "Hari3",
    "link": "https://editor.p5js.org/HariKrishnan/present/uGdTrs9uB",
    "title": "",
    "authorURL": "",
    "challengeURL": ""
  },
  {
    "Number": 30,
    "Original Challenge": "tic tac toe",
    "contributor": "atasoglu",
    "link": "https://editor.p5js.org/atasoglu/present/ih2JEeRj5",
    "title": "",
    "authorURL": "",
    "challengeURL": ""
  },
  {
    "Number": 31,
    "Original Challenge": "forward kinematics",
    "contributor": "David Snyder",
    "link": "https://www.youtube.com/watch?v=XrhZvpvP4a4",
    "title": "",
    "authorURL": "",
    "challengeURL": ""
  },
  {
    "Number": 32,
    "Original Challenge": "maze generator",
    "contributor": "sylvainberube",
    "link": "https://editor.p5js.org/sylvainberube/present/doxwlc9US",
    "title": "",
    "authorURL": "",
    "challengeURL": ""
  },
  {
    "Number": 33,
    "Original Challenge": "tic tac toe",
    "contributor": "IMPorbis",
    "link": "https://editor.p5js.org/IMPorbis/present/rH9vPGABt",
    "title": "",
    "authorURL": "",
    "challengeURL": ""
  },
  {
    "Number": 34,
    "Original Challenge": "floyd-steinberg-dithering",
    "contributor": "David Snyder",
    "link": "https://editor.p5js.org/davidgraygs4@gmail.com/present/96wsqZdh6",
    "title": "",
    "authorURL": "",
    "challengeURL": ""
  },
  {
    "Number": 35,
    "Original Challenge": "chrome dino game",
    "contributor": "leimapapa",
    "link": "https://codepen.io/leimapapa/pen/zVoJWz",
    "title": "",
    "authorURL": "",
    "challengeURL": ""
  },
  {
    "Number": 36,
    "Original Challenge": "perlin noise loops",
    "contributor": "leimapapa",
    "link": "https://codepen.io/leimapapa/pen/gEMGPr",
    "title": "",
    "authorURL": "",
    "challengeURL": ""
  },
  {
    "Number": 37,
    "Original Challenge": "timer",
    "contributor": "leimapapa",
    "link": "https://codepen.io/leimapapa/pen/qeaWoP",
    "title": "",
    "authorURL": "",
    "challengeURL": ""
  },
  {
    "Number": 38,
    "Original Challenge": "asteroids",
    "contributor": "dmfabritius",
    "link": "https://editor.p5js.org/dmfabritius/present/jdcQ8K0ho",
    "title": "",
    "authorURL": "",
    "challengeURL": ""
  },
  {
    "Number": 39,
    "Original Challenge": "sentiment analysis",
    "contributor": "leimapapa",
    "link": "https://codepen.io/leimapapa/pen/JwWYKo",
    "title": "",
    "authorURL": "",
    "challengeURL": ""
  },
  {
    "Number": 40,
    "Original Challenge": "10print",
    "contributor": "neerb",
    "link": "https://editor.p5js.org/neerb/present/k4_2WOkRe",
    "title": "",
    "authorURL": "",
    "challengeURL": ""
  },
  {
    "Number": 41,
    "Original Challenge": "phyllotaxis",
    "contributor": "leimapapa",
    "link": "https://codepen.io/leimapapa/pen/yZKyoq",
    "title": "",
    "authorURL": "",
    "challengeURL": ""
  },
  {
    "Number": 42,
    "Original Challenge": "smart rockets",
    "contributor": "leimapapa",
    "link": "https://codepen.io/leimapapa/pen/QJwjwE",
    "title": "",
    "authorURL": "",
    "challengeURL": ""
  },
  {
    "Number": 43,
    "Original Challenge": "markov chain",
    "contributor": "leimapapa",
    "link": "https://codepen.io/leimapapa/pen/gNozyp",
    "title": "",
    "authorURL": "",
    "challengeURL": ""
  },
  {
    "Number": 44,
    "Original Challenge": "tic tac toe",
    "contributor": "JeanLoup",
    "link": "https://editor.p5js.org/JeanLoup/present/3AOnKAWfF",
    "title": "",
    "authorURL": "",
    "challengeURL": ""
  },
  {
    "Number": 45,
    "Original Challenge": "10print",
    "contributor": "Volfegan",
    "link": "https://www.youtube.com/watch?v=7v4I519CL-g",
    "title": "",
    "authorURL": "",
    "challengeURL": ""
  },
  {
    "Number": 46,
    "Original Challenge": "perlin noise loops",
    "contributor": "yusukesaitoh",
    "link": "https://www.openprocessing.org/sketch/739862",
    "title": "",
    "authorURL": "",
    "challengeURL": ""
  },
  {
    "Number": 47,
    "Original Challenge": "clock",
    "contributor": "abhijeetmankani",
    "link": "https://editor.p5js.org/abhijeetmankani/present/WKtYu4-Cd",
    "title": "",
    "authorURL": "",
    "challengeURL": ""
  },
  {
    "Number": 48,
    "Original Challenge": "particle system",
    "contributor": "veotaar",
    "link": "https://www.openprocessing.org/sketch/459864",
    "title": "",
    "authorURL": "",
    "challengeURL": ""
  },
  {
    "Number": 49,
    "Original Challenge": "tic tac toe",
    "contributor": "Udit_sharma",
    "link": "https://editor.p5js.org/Udit_sharma/present/JCP2GzDRp",
    "title": "",
    "authorURL": "",
    "challengeURL": ""
  },
  {
    "Number": 50,
    "Original Challenge": "space invaders",
    "contributor": "minoger",
    "link": "https://editor.p5js.org/minoger/present/ul4KYn9JP",
    "title": "",
    "authorURL": "",
    "challengeURL": ""
  },
  {
    "Number": 51,
    "Original Challenge": "tic tac toe",
    "contributor": "ClaudiuC",
    "link": "https://editor.p5js.org/ClaudiuC/present/yaHlzPc9x",
    "title": "",
    "authorURL": "",
    "challengeURL": ""
  },
  {
    "Number": 52,
    "Original Challenge": "fractal tree",
    "contributor": "imtusharsharma",
    "link": "https://editor.p5js.org/imtusharsharma/present/FcyznC4KW",
    "title": "",
    "authorURL": "",
    "challengeURL": ""
  },
  {
    "Number": 53,
    "Original Challenge": "convex hull",
    "contributor": "KeesKolber",
    "link": "https://editor.p5js.org/KeesKolber/present/bzvB_7qKf",
    "title": "",
    "authorURL": "",
    "challengeURL": ""
  },
  {
    "Number": 54,
    "Original Challenge": "random walk",
    "contributor": "hanxyn888",
    "link": "https://editor.p5js.org/hanxyn888@gmail.com/present/uSlG5StqX",
    "title": "",
    "authorURL": "",
    "challengeURL": ""
  },
  {
    "Number": 55,
    "Original Challenge": "wordnik api",
    "contributor": "mikakruschel",
    "link": "https://editor.p5js.org/mikakruschel/present/SJD4mWnAX",
    "title": "",
    "authorURL": "",
    "challengeURL": ""
  },
  {
    "Number": 56,
    "Original Challenge": "blobby",
    "contributor": "jponce",
    "link": "https://editor.p5js.org/jcponce/present/cWHhxwgxl",
    "title": "",
    "authorURL": "",
    "challengeURL": ""
  },
  {
    "Number": 57,
    "Original Challenge": "clock",
    "contributor": "martin",
    "link": "https://editor.p5js.org/martin@multiarts.ch/present/Hk3o7UQ07",
    "title": "",
    "authorURL": "",
    "challengeURL": ""
  },
  {
    "Number": 58,
    "Original Challenge": "tic tac toe",
    "contributor": "ilmnarayana",
    "link": "https://editor.p5js.org/ilmnarayana/present/_-JTT51Qt",
    "title": "",
    "authorURL": "",
    "challengeURL": ""
  },
  {
    "Number": 59,
    "Original Challenge": "convex hull",
    "contributor": "Guy_Yome",
    "link": "https://editor.p5js.org/Guy_Yome/present/-73RZAaRJ",
    "title": "",
    "authorURL": "",
    "challengeURL": ""
  },
  {
    "Number": 60,
    "Original Challenge": "minesweeper",
    "contributor": "claesgill",
    "link": "http://www.claesgill.com/trollsweeper/",
    "title": "",
    "authorURL": "",
    "challengeURL": ""
  },
  {
    "Number": 61,
    "Original Challenge": "tic tac toe",
    "contributor": "AmritAmar",
    "link": "https://editor.p5js.org/AmritAmar/present/x2dtFTAsH",
    "title": "",
    "authorURL": "",
    "challengeURL": ""
  },
  {
    "Number": 62,
    "Original Challenge": "ai steering behaviors",
    "contributor": "gmanen",
    "link": "https://editor.p5js.org/gmanen/present/HF0OH8ATr",
    "title": "",
    "authorURL": "",
    "challengeURL": ""
  },
  {
    "Number": 63,
    "Original Challenge": "flappy bird ai",
    "contributor": "sebastien lorentz",
    "link": "https://editor.p5js.org/sebastien.lorentz/present/ht-gL0Z4o",
    "title": "",
    "authorURL": "",
    "challengeURL": ""
  },
  {
    "Number": 64,
    "Original Challenge": 2048,
    "contributor": "David Snyder",
    "link": "https://editor.p5js.org/davidgraygs4@gmail.com/present/zMhaJYxmc",
    "title": "",
    "authorURL": "",
    "challengeURL": ""
  },
  {
    "Number": 65,
    "Original Challenge": "flappy bird ai",
    "contributor": "ernst-schmidt",
    "link": "https://www.ernst-schmidt.com/coding/5d30690dc7a6e90017a94ef6",
    "title": "",
    "authorURL": "",
    "challengeURL": ""
  },
  {
    "Number": 66,
    "Original Challenge": "flocking system",
    "contributor": "ernst-schmidt",
    "link": "https://www.ernst-schmidt.com/coding/5d70ea631d0a070017666552",
    "title": "",
    "authorURL": "",
    "challengeURL": ""
  },
  {
    "Number": 67,
    "Original Challenge": "raycasting",
    "contributor": "meznak",
    "link": "https://www.youtube.com/watch?v=JoYN-UGypSg&feature=youtu.be",
    "title": "",
    "authorURL": "",
    "challengeURL": ""
  },
  {
    "Number": 68,
    "Original Challenge": "starfield",
    "contributor": "AminCodingChallenge",
    "link": "https://editor.p5js.org/AminCodingChallenge/present/aoIBBYSgY",
    "title": "",
    "authorURL": "",
    "challengeURL": ""
  },
  {
    "Number": 69,
    "Original Challenge": "raycasting",
    "contributor": "David Snyder",
    "link": "https://editor.p5js.org/davidgraygs4@gmail.com/present/oUXmojdXi",
    "title": "",
    "authorURL": "",
    "challengeURL": ""
  },
  {
    "Number": 70,
    "Original Challenge": "menger sponge",
    "contributor": "AminCodingChallenge",
    "link": "https://editor.p5js.org/AminCodingChallenge/present/3S1QjYwAy",
    "title": "",
    "authorURL": "",
    "challengeURL": ""
  },
  {
    "Number": 71,
    "Original Challenge": "snake",
    "contributor": "AminCodingChallenge",
    "link": "https://editor.p5js.org/AminCodingChallenge/present/9QYlaqrgV",
    "title": "",
    "authorURL": "",
    "challengeURL": ""
  },
  {
    "Number": 72,
    "Original Challenge": "purple rain",
    "contributor": "AminCodingChallenge",
    "link": "https://editor.p5js.org/AminCodingChallenge/present/hxRaq59Xt",
    "title": "",
    "authorURL": "",
    "challengeURL": ""
  },
  {
    "Number": 73,
    "Original Challenge": "space invaders",
    "contributor": "AminCodingChallenge",
    "link": "https://editor.p5js.org/AminCodingChallenge/present/U3xEo8Ifg",
    "title": "",
    "authorURL": "",
    "challengeURL": ""
  },
  {
    "Number": 74,
    "Original Challenge": "mitosis",
    "contributor": "AminCodingChallenge",
    "link": "https://editor.p5js.org/AminCodingChallenge/present/nUyR3Xnpf",
    "title": "",
    "authorURL": "",
    "challengeURL": ""
  },
  {
    "Number": 75,
    "Original Challenge": "hypercube",
    "contributor": "David Snyder",
    "link": "https://editor.p5js.org/davidgraygs4@gmail.com/present/492uCszzp",
    "title": "",
    "authorURL": "",
    "challengeURL": ""
  },
  {
    "Number": 76,
    "Original Challenge": "project 3d to 2d",
    "contributor": "David Snyder",
    "link": "https://editor.p5js.org/davidgraygs4@gmail.com/present/n3YFHyz0D",
    "title": "",
    "authorURL": "",
    "challengeURL": ""
  },
  {
    "Number": 77,
    "Original Challenge": "Minesweeper",
    "contributor": "David Snyder",
    "link": "https://GypsyDangerous.github.io/Minesweeper-React/",
    "title": "",
    "authorURL": "",
    "challengeURL": ""
  },
  {
    "Number": 78,
    "Original Challenge": "peeking inside pi",
    "contributor": "arnavsirigere",
    "link": "https://editor.p5js.org/Arnav-Sirigere/present/d3e6yoeA",
    "title": "",
    "authorURL": "",
    "challengeURL": ""
  },
  {
    "Number": 79,
    "Original Challenge": "quicksort",
    "contributor": "jbud",
    "link": "https://editor.p5js.org/budzique/present/eL779ZiF",
    "title": "",
    "authorURL": "",
    "challengeURL": ""
  },
  {
    "Number": 80,
    "Original Challenge": "convex hull",
    "contributor": "arthurrcavalcanti",
    "link": "https://editor.p5js.org/arthurrc/present/OldqKcL5",
    "title": "",
    "authorURL": "",
    "challengeURL": ""
  },
  {
    "Number": 81,
    "Original Challenge": "clock",
    "contributor": "Morphinepill",
    "link": "https://editor.p5js.org/Morphinepill/present/UFsFBd1Z",
    "title": "",
    "authorURL": "",
    "challengeURL": ""
  },
  {
    "Number": 82,
    "Original Challenge": "heart curve",
    "contributor": "AnonymousPyro",
    "link": "https://editor.p5js.org/AnonymousPyro/present/Q2XUJXm5",
    "title": "",
    "authorURL": "",
    "challengeURL": ""
  },
  {
    "Number": 83,
    "Original Challenge": "heart curve",
    "contributor": "AnonymousPyro",
    "link": "https://editor.p5js.org/AnonymousPyro/present/klkuDmy4",
    "title": "",
    "authorURL": "",
    "challengeURL": ""
  },
  {
    "Number": 84,
    "Original Challenge": "snake",
    "contributor": "David Snyder",
    "link": "https://editor.p5js.org/D_Snyder/present/dccXgYaes",
    "title": "",
    "authorURL": "",
    "challengeURL": ""
  },
  {
    "Number": 85,
    "Original Challenge": "matrix rain / clock",
    "contributor": "David Snyder",
    "link": "https://editor.p5js.org/D_Snyder/present/QTjGNty-6",
    "title": "",
    "authorURL": "",
    "challengeURL": ""
  },
  {
    "Number": 86,
    "Original Challenge": "block breaker with yinig shi",
    "contributor": "David Snyder",
    "link": "https://editor.p5js.org/D_Snyder/present/GFvxMbs9t",
    "title": "",
    "authorURL": "",
    "challengeURL": ""
  },
  {
    "Number": 87,
    "Original Challenge": "fireworks",
    "contributor": "arnavsirigere",
    "link": "https://editor.p5js.org/Arnav-Sirigere/present/gHb_ytBvB",
    "title": "",
    "authorURL": "",
    "challengeURL": ""
  },
  {
    "Number": 88,
    "Original Challenge": "random walks",
    "contributor": "arnavsirigere",
    "link": "https://editor.p5js.org/Arnav-Sirigere/present/0iRp-6BRt",
    "title": "",
    "authorURL": "",
    "challengeURL": ""
  },
  {
    "Number": 89,
    "Original Challenge": "starfield",
    "contributor": "BossySmaxx",
    "link": "https://asteroidfield.glitch.me/",
    "title": "",
    "authorURL": "",
    "challengeURL": ""
  },
  {
    "Number": 90,
    "Original Challenge": "flocking system",
    "contributor": "leimapapa",
    "link": "https://codepen.io/leimapapa/pen/abzZLBy",
    "title": "",
    "authorURL": "",
    "challengeURL": ""
  },
  {
    "Number": 91,
    "Original Challenge": "flocking system",
    "contributor": "arnavsirigere",
    "link": "https://editor.p5js.org/Arnav-Sirigere/present/FMBzzf5Vd",
    "title": "",
    "authorURL": "",
    "challengeURL": ""
  },
  {
    "Number": 92,
    "Original Challenge": "times tables",
    "contributor": "Szymon300101",
    "link": "https://szymon300101.github.io/TableFlow/",
    "title": "",
    "authorURL": "",
    "challengeURL": ""
  },
  {
    "Number": 93,
    "Original Challenge": "pong",
    "contributor": "mragonias",
    "link": "https://editor.p5js.org/mragonias/present/yTDYn8pt",
    "title": "",
    "authorURL": "",
    "challengeURL": ""
  },
  {
    "Number": 94,
    "Original Challenge": "snakes and ladders",
    "contributor": "kobe",
    "link": "https://editor.p5js.org/KobeL/present/u_AYfmVX",
    "title": "",
    "authorURL": "",
    "challengeURL": ""
  },
  {
    "Number": 95,
    "Original Challenge": "game of life",
    "contributor": "kobe",
    "link": "https://editor.p5js.org/KobeL/present/i6wwDC6B",
    "title": "",
    "authorURL": "",
    "challengeURL": ""
  },
  {
    "Number": 96,
    "Original Challenge": "game of life (again)",
    "contributor": "kobe",
    "link": "https://editor.p5js.org/KobeL/present/UIHG9Drw",
    "title": "",
    "authorURL": "",
    "challengeURL": ""
  },
  {
    "Number": 97,
    "Original Challenge": "pong",
    "contributor": "kobe",
    "link": "https://editor.p5js.org/D_Snyder/present/4Ur5Y5Gd",
    "title": "",
    "authorURL": "",
    "challengeURL": ""
  },
  {
    "Number": 98,
    "Original Challenge": "maurer rose",
    "contributor": "dwino",
    "link": "https://editor.p5js.org/dwino/present/O2xBcdksk",
    "title": "",
    "authorURL": "",
    "challengeURL": ""
  },
  {
    "Number": 99,
    "Original Challenge": "maurer rose",
    "contributor": "stampyzfanz",
    "link": "https://stampyzfanz.github.io/games/MaurerRose/",
    "title": "",
    "authorURL": "",
    "challengeURL": ""
  },
  {
    "Number": 100,
    "Original Challenge": "maurer rose",
    "contributor": "sequentialchaos",
    "link": "https://editor.p5js.org/sequentialchaos/present/Zq70Kbrmk",
    "title": "",
    "authorURL": "",
    "challengeURL": ""
  },
  {
    "Number": 101,
    "Original Challenge": "sprites",
    "contributor": "David Snyder",
    "link": "https://editor.p5js.org/D_Snyder/present/t54D7ohz",
    "title": "",
    "authorURL": "",
    "challengeURL": ""
  },
  {
    "Number": 102,
    "Original Challenge": "koch snowflake",
    "contributor": "anuraghazra",
    "link": "https://anuraghazra.github.io/CanvasFun/KochStar/",
    "title": "",
    "authorURL": "",
    "challengeURL": ""
  },
  {
    "Number": 103,
    "Original Challenge": "chat bot",
    "contributor": "David Snyder",
    "link": "https://gypsydangerous.github.io/number-guessing-bot/",
    "title": "",
    "authorURL": "",
    "challengeURL": ""
  },
  {
    "Number": 104,
    "Original Challenge": "pong",
    "contributor": "David Snyder",
    "link": "https://editor.p5js.org/D_Snyder/present/TqeYYpRuu",
    "title": "",
    "authorURL": "",
    "challengeURL": ""
  },
  {
    "Number": 105,
    "Original Challenge": "tic tac toe",
    "contributor": "David Snyder",
    "link": "https://ticonlinetactoe.herokuapp.com/",
    "title": "",
    "authorURL": "",
    "challengeURL": ""
  }
]